CONTRIBUTING.rst
HISTORY.rst
LICENSE
MANIFEST.in
README.rst
gendocstr.py
pystrict3.py
setup.cfg
setup.py
pystrict3.egg-info/PKG-INFO
pystrict3.egg-info/SOURCES.txt
pystrict3.egg-info/dependency_links.txt
pystrict3.egg-info/requires.txt
pystrict3.egg-info/top_level.txt
pystrict3lib/__init__.py
pystrict3lib/classchecker.py
pystrict3lib/funcchecker.py
tests/test_docrefs.py
tests/test_docstrings.py
tests/test_generate.py
tests/test_overwrites.py