Metadata-Version: 2.1
Name: pystrict3
Version: 1.0.1
Summary: Static code analyser for Python3 function calls, string interpolation and variable shadowing
Home-page: https://github.com/JohannesBuchner/pystrict3
Author: Johannes Buchner
Author-email: johannes.buchner.acad@gmx.com
License: BSD
Classifier: Development Status :: 5 - Production/Stable
Classifier: Intended Audience :: Developers
Classifier: License :: OSI Approved :: GNU General Public License v3 (GPLv3)
Classifier: Natural Language :: English
Classifier: Programming Language :: Python :: 3
Classifier: Programming Language :: Python :: 3.5
Classifier: Programming Language :: Python :: 3.6
Classifier: Programming Language :: Python :: 3.7
Classifier: Programming Language :: Python :: 3.8
Requires-Python: >=3.7
License-File: LICENSE
